waggle/__init__.py
waggle/waggle.py
waggle-0.2.4.dist-info/DESCRIPTION.rst
waggle-0.2.4.dist-info/METADATA
waggle-0.2.4.dist-info/RECORD
waggle-0.2.4.dist-info/WHEEL
waggle-0.2.4.dist-info/entry_points.txt
waggle-0.2.4.dist-info/metadata.json
waggle-0.2.4.dist-info/top_level.txt
