Metadata-Version: 2.0
Name: waggle
Version: 0.2.4
Summary: Tools for a BeeKeeper worker drone to report status back to the hive.
Home-page: http://pybee.org/waggle
Author: Russell Keith-Magee
Author-email: russell@keith-magee.com
License: New BSD
Keywords: beekeeper
Platform: UNKNOWN
Classifier: Development Status :: 4 - Beta
Classifier: Intended Audience :: Developers
Classifier: License :: OSI Approved :: BSD License
Classifier: Operating System :: OS Independent
Classifier: Programming Language :: Python :: 3
Classifier: Programming Language :: Python :: 3.4
Classifier: Programming Language :: Python :: 3.5
Classifier: Programming Language :: Python :: 3.6
Classifier: Topic :: Software Development
Classifier: Topic :: Utilities
Requires-Dist: github3.py
Requires-Dist: boto3
Requires-Dist: awscli
